s3_connection/__init__.py
s3_connection/s3_conn_class.py
s3_connection-0.1.2.dist-info/LICENSE
s3_connection-0.1.2.dist-info/METADATA
s3_connection-0.1.2.dist-info/WHEEL
s3_connection-0.1.2.dist-info/top_level.txt
s3_connection-0.1.2.dist-info/RECORD
