Metadata-Version: 2.1
Name: s3-connection
Version: 0.1.2
Summary: A package with functions for reading/writing different file types from/to AWS S3 storage. It is essentially a wrapper for the s3fs package.
Author: Jamie O'Brien
License: UNKNOWN
Platform: UNKNOWN
License-File: LICENSE
Requires-Dist: s3fs (>=2022.2.0)
Requires-Dist: tensorflow (>=2.8.0)
Requires-Dist: pandas (>=1.3.4)
